{
  "success": true,
  "title": "竞品分析怎么做？6年亚马逊老运营教你一键拆解爆款打法",
  "content": "大家好，我是阿澄，已经在深圳做了6年亚马逊运营，在此和大家分享我的职场成长以及日常生活。\n所谓知己知彼百战百胜，在亚马逊这个越来越卷的跨境电商市场上，与其每天两眼一睁就是焦虑地盯着广告ACOS，陷入新品推不起、老品不稳定的恶性循环，每天都为过山车似的销量而忧愁，不如把思维跳出自己的产品，多分析一下竞品的做法，将好的方法运用与自己的产品上面。\n真正的竞品分析不是仅仅停留在表面，靠抄一下竞品的标题和图片，就以为是在分析竞品、汲取了竞争对手的精华，这不过是在自我感动，对产品销量的推进没有实质性作用。\n精准的竞品分析、竞品拆解才能有效帮助我们把产品推上去，今天阿澄就和大家分享一下自己的竞品分析、拆解方法，都是个人经验所谈。\n竞品分析第一步就是要找对分析的对象\n竞品分析不是什么竞品都盯着看，有的亚马逊运营就喜欢盯着类目第一、第二名的产品。\n但是大家这样子做的时候有没有想过，这样子定对标竞品的实际意义有多少？就好比你做3C，你一上来就是天天盯着安克创新的产品看，你了解这个3C巨头做到这个位置上，需要多大的团队、供应链支持、资金支持、站外推广？再者就是它的品牌溢价，毫不夸张地说提到3C基本都会想到安克创新的产品。要做到这些不是一朝一夕，每个环节的巨额投入，你是学不来的。\n真正值得天天盯、拆解打法的是与自己同级层次的竞品、类目榜单突然飙上来的黑马竞品。\n第一类与自己同级层次的竞品，值得去深挖的是同等定价、功能、设计、体量，但是销量却比你的产品好的产品，它优于你的地方就是你需要学习的地方，也是销量增长的关键点。\n第二类则是类目榜单突然飙上来的黑马竞品，这一类产品也是比较具备潜力的产品，这类竞品的特点是上架时间比较短，通常在3-6个月之内、评论数量也比较少，但是它显著的优势就是在短期内BSR排名上升得比较快。这说明它精准找到了产品的流量入口、匹配的打法以及差异化优势。摸透它这几个点的做法，再去学习这种做法，对我们推新有很大的帮助。\n竞品分析第二步就是要摸透流量来源\n销量、排名增长快是竞品的结果，流量结构才是核心，要看到背后是怎么操作在短时内吸引大量买家购买它的产品。\n通俗来说就是关键词、主要的流量入口。关键词可以通过相关工具做关键词反查，去看竞品的核心流量词、核心长尾词，并且现在的工具已经升级到直接可以看到反查ASIN哪个阶段开了哪些类型的广告，把这些数据总结下来，就可以反推竞品的推广节奏、广告结构。\n流量入口主要就分为亚马逊站内和站外。站内就是我们比较熟知的自然搜索流量、关联流量、优惠券、促销、秒杀等等；站外就是deals、fb群组推广等等。\n竞品分析第三步就是深挖产品痛点\n对产品迭代、优化链接的最重要环节，分析、拆解竞品的每一个差评，这里面隐藏着你弯道超车的好机会。\n1-3星的差评基本都将产品的功能短板、设计短板、材质、安装等等核心要素的缺点暴露出来了。在选品、迭代升级的时候核心做优化，在优化链接的时候重点阐述买家在意的痛点、突出你的产品解决了哪些痛点、又是如何解决的。\n4-5星的好评主要反馈了买家很在意又比较满意的核心需求，这就是产品标题、五点精准流量关键词的来源，通过这样子的方式得出来的关键词比你自己胡乱弄来的卖点要靠谱、精准得多。\n竞品分析第四步就是要反推竞品打法的成本\n简言之就是竞品突然推起来是因为正常的推广，还是因为亏本的清仓形成抢眼的低价，又或者是因为在站外做了低价放量。\n再者关注竞品的价格曲线，如果它的价格曲线显示售价长期低于类目平均水平。那你就要好好算一笔账，低价亏本吆喝，要么就是清仓、要么就是亏本冲排名。\n这种长期亏本的做法，我们要三思，想清楚盲目跟风会带来哪些后果。更值得我们学习、模仿的是正常将产品推起来，后期有可持续利润的方法，而不是盲目追求排名和销量。\n换句话来说，不计成本地冲排名，只要你敢，是很容易做到的，但是产品没有实际推起来，销量与排名也不是良性、可持续性的。\n推品的成功经验都是拆解、实践出来的，希望我的分享能够对大家有所启发。\n今天的分享就到这里啦！接下来的日子，我会在「阿澄在深圳」继续记录我的职场成长和生活日常，也聊聊在深圳打工的真实感受。",
  "publish_time": "",
  "source": "",
  "url": "https://mp.weixin.qq.com/s/DeJ4cX7yf71I82pTF8S8JA",
  "cover": "https://mmbiz.qpic.cn/mmbiz_jpg/78yCr2iaefd1Cpic7n5wicvWibiae1DTI9U619SvgN07NNsP0VNa4OI0NsYj74FZZB4XVL2Usiacsac3bziaibQP9zYfzUCMibW3wsziasyrqA8TzLuDw/0?wx_fmt=jpeg",
  "word_count": 1710,
  "fetch_time": "2026-05-28 18:24:53"
}